{
    "一些": {
        "draw": false,
        "times": 3
    },
    "一個": {
        "draw": false,
        "times": 13
    },
    "一千": {
        "draw": false,
        "times": 1
    },
    "一門": {
        "draw": false,
        "times": 1
    },
    "三三加": {
        "draw": false,
        "times": 1
    },
    "三個": {
        "draw": false,
        "times": 4
    },
    "下": {
        "draw": false,
        "times": 3
    },
    "下雨": {
        "draw": false,
        "times": 1
    },
    "不到": {
        "draw": false,
        "times": 1
    },
    "不好": {
        "draw": false,
        "times": 4
    },
    "不好意思": {
        "draw": false,
        "times": 4
    },
    "不想": {
        "draw": false,
        "times": 4
    },
    "中": {
        "draw": false,
        "times": 3
    },
    "中午": {
        "draw": false,
        "times": 2
    },
    "中文": {
        "draw": false,
        "times": 1
    },
    "中職": {
        "draw": false,
        "times": 2
    },
    "丼": {
        "draw": false,
        "times": 1
    },
    "之外": {
        "draw": false,
        "times": 1
    },
    "之後": {
        "draw": false,
        "times": 3
    },
    "了解": {
        "draw": false,
        "times": 2
    },
    "五分鐘": {
        "draw": false,
        "times": 1
    },
    "亞昕": {
        "draw": false,
        "times": 1
    },
    "人": {
        "draw": false,
        "times": 4
    },
    "人太": {
        "draw": false,
        "times": 1
    },
    "人數": {
        "draw": false,
        "times": 1
    },
    "今天": {
        "draw": false,
        "times": 3
    },
    "今年": {
        "draw": false,
        "times": 5
    },
    "他會": {
        "draw": false,
        "times": 1
    },
    "他講": {
        "draw": false,
        "times": 1
    },
    "以上": {
        "draw": false,
        "times": 3
    },
    "低": {
        "draw": false,
        "times": 4
    },
    "作戰": {
        "draw": false,
        "times": 1
    },
    "你好": {
        "draw": false,
        "times": 3
    },
    "來來": {
        "draw": false,
        "times": 1
    },
    "信用卡": {
        "draw": false,
        "times": 4
    },
    "做": {
        "draw": false,
        "times": 4
    },
    "停掉": {
        "draw": false,
        "times": 1
    },
    "傻蛋": {
        "draw": false,
        "times": 1
    },
    "像是": {
        "draw": false,
        "times": 1
    },
    "元智": {
        "draw": false,
        "times": 1
    },
    "先": {
        "draw": false,
        "times": 3
    },
    "先知": {
        "draw": false,
        "times": 1
    },
    "先進": {
        "draw": false,
        "times": 1
    },
    "兩": {
        "draw": false,
        "times": 2
    },
    "兩兩": {
        "draw": false,
        "times": 1
    },
    "兩萬": {
        "draw": false,
        "times": 2
    },
    "兩隻": {
        "draw": false,
        "times": 3
    },
    "再": {
        "draw": false,
        "times": 1
    },
    "再也": {
        "draw": false,
        "times": 1
    },
    "再來": {
        "draw": false,
        "times": 3
    },
    "再開": {
        "draw": false,
        "times": 1
    },
    "刁鑽": {
        "draw": false,
        "times": 1
    },
    "分": {
        "draw": false,
        "times": 1
    },
    "分享": {
        "draw": false,
        "times": 2
    },
    "分擔": {
        "draw": false,
        "times": 1
    },
    "分燙": {
        "draw": false,
        "times": 1
    },
    "分鐘": {
        "draw": false,
        "times": 1
    },
    "前進": {
        "draw": false,
        "times": 2
    },
    "功能": {
        "draw": false,
        "times": 5
    },
    "加": {
        "draw": false,
        "times": 1
    },
    "原來": {
        "draw": false,
        "times": 2
    },
    "原因": {
        "draw": false,
        "times": 1
    },
    "只會": {
        "draw": false,
        "times": 1
    },
    "台": {
        "draw": false,
        "times": 2
    },
    "台灣": {
        "draw": false,
        "times": 20
    },
    "台灣的幣": {
        "draw": false,
        "times": 1
    },
    "台灣的磚": {
        "draw": false,
        "times": 1
    },
    "吃": {
        "draw": false,
        "times": 3
    },
    "名": {
        "draw": false,
        "times": 1
    },
    "品質": {
        "draw": false,
        "times": 5
    },
    "員": {
        "draw": false,
        "times": 1
    },
    "唱": {
        "draw": false,
        "times": 1
    },
    "四邊": {
        "draw": false,
        "times": 1
    },
    "國內": {
        "draw": false,
        "times": 2
    },
    "國外": {
        "draw": false,
        "times": 5
    },
    "在國": {
        "draw": false,
        "times": 1
    },
    "坐下": {
        "draw": false,
        "times": 1
    },
    "坐姿": {
        "draw": false,
        "times": 2
    },
    "外環": {
        "draw": false,
        "times": 1
    },
    "大安": {
        "draw": false,
        "times": 2
    },
    "大愛": {
        "draw": false,
        "times": 1
    },
    "大戰": {
        "draw": false,
        "times": 1
    },
    "大樂透": {
        "draw": false,
        "times": 1
    },
    "大陸": {
        "draw": false,
        "times": 2
    },
    "太": {
        "draw": false,
        "times": 1
    },
    "太貴": {
        "draw": false,
        "times": 4
    },
    "太輕": {
        "draw": false,
        "times": 4
    },
    "奶奶": {
        "draw": false,
        "times": 1
    },
    "姐姐": {
        "draw": false,
        "times": 1
    },
    "媽": {
        "draw": false,
        "times": 2
    },
    "媽媽": {
        "draw": false,
        "times": 2
    },
    "安心": {
        "draw": false,
        "times": 3
    },
    "安養": {
        "draw": false,
        "times": 1
    },
    "完": {
        "draw": false,
        "times": 1
    },
    "家": {
        "draw": false,
        "times": 2
    },
    "家事": {
        "draw": false,
        "times": 1
    },
    "實在": {
        "draw": false,
        "times": 1
    },
    "寺": {
        "draw": false,
        "times": 1
    },
    "專家": {
        "draw": false,
        "times": 4
    },
    "專輯": {
        "draw": false,
        "times": 1
    },
    "對方": {
        "draw": false,
        "times": 4
    },
    "小說": {
        "draw": false,
        "times": 4
    },
    "希望": {
        "draw": false,
        "times": 7
    },
    "平價": {
        "draw": false,
        "times": 2
    },
    "年紀": {
        "draw": false,
        "times": 5
    },
    "年終": {
        "draw": false,
        "times": 1
    },
    "建立": {
        "draw": false,
        "times": 5
    },
    "張": {
        "draw": false,
        "times": 1
    },
    "張家": {
        "draw": false,
        "times": 1
    },
    "愛": {
        "draw": false,
        "times": 1
    },
    "我要": {
        "draw": false,
        "times": 1
    },
    "打來": {
        "draw": false,
        "times": 1
    },
    "扯": {
        "draw": false,
        "times": 4
    },
    "抽": {
        "draw": false,
        "times": 7
    },
    "拉門": {
        "draw": false,
        "times": 1
    },
    "拜託": {
        "draw": false,
        "times": 3
    },
    "挑食": {
        "draw": false,
        "times": 1
    },
    "推倒": {
        "draw": false,
        "times": 1
    },
    "措施": {
        "draw": false,
        "times": 2
    },
    "教室": {
        "draw": false,
        "times": 1
    },
    "新加坡": {
        "draw": false,
        "times": 4
    },
    "新增": {
        "draw": false,
        "times": 1
    },
    "方便": {
        "draw": false,
        "times": 4
    },
    "時間": {
        "draw": false,
        "times": 1
    },
    "晚上": {
        "draw": false,
        "times": 4
    },
    "暗": {
        "draw": false,
        "times": 1
    },
    "曼谷": {
        "draw": false,
        "times": 3
    },
    "月底": {
        "draw": false,
        "times": 4
    },
    "有時候": {
        "draw": false,
        "times": 1
    },
    "服務": {
        "draw": false,
        "times": 2
    },
    "本會": {
        "draw": false,
        "times": 2
    },
    "東南亞": {
        "draw": false,
        "times": 3
    },
    "松露": {
        "draw": false,
        "times": 2
    },
    "梵唄": {
        "draw": false,
        "times": 1
    },
    "步伐": {
        "draw": false,
        "times": 1
    },
    "民眾": {
        "draw": false,
        "times": 1
    },
    "沒事": {
        "draw": false,
        "times": 4
    },
    "泰國": {
        "draw": false,
        "times": 3
    },
    "活動": {
        "draw": false,
        "times": 8
    },
    "海外華人": {
        "draw": false,
        "times": 4
    },
    "海鮮": {
        "draw": false,
        "times": 2
    },
    "無彩限": {
        "draw": false,
        "times": 1
    },
    "熱": {
        "draw": false,
        "times": 1
    },
    "熱就": {
        "draw": false,
        "times": 1
    },
    "熱處理": {
        "draw": false,
        "times": 1
    },
    "燙": {
        "draw": false,
        "times": 1
    },
    "營養師": {
        "draw": false,
        "times": 3
    },
    "版本": {
        "draw": false,
        "times": 2
    },
    "玩": {
        "draw": false,
        "times": 1
    },
    "玩亞": {
        "draw": false,
        "times": 1
    },
    "玩亞先": {
        "draw": false,
        "times": 1
    },
    "病患": {
        "draw": true,
        "times": 3
    },
    "發現": {
        "draw": false,
        "times": 4
    },
    "的花海": {
        "draw": false,
        "times": 1
    },
    "目標": {
        "draw": false,
        "times": 1
    },
    "直播": {
        "draw": false,
        "times": 1
    },
    "知道": {
        "draw": false,
        "times": 6
    },
    "第一": {
        "draw": false,
        "times": 1
    },
    "算": {
        "draw": false,
        "times": 2
    },
    "管道": {
        "draw": false,
        "times": 2
    },
    "紅包": {
        "draw": false,
        "times": 4
    },
    "結束": {
        "draw": false,
        "times": 3
    },
    "緊張": {
        "draw": false,
        "times": 3
    },
    "編制": {
        "draw": false,
        "times": 1
    },
    "聲音": {
        "draw": false,
        "times": 3
    },
    "聽": {
        "draw": false,
        "times": 1
    },
    "肺結核": {
        "draw": true,
        "times": 1
    },
    "興趣": {
        "draw": false,
        "times": 1
    },
    "航海王": {
        "draw": false,
        "times": 1
    },
    "華人": {
        "draw": false,
        "times": 2
    },
    "華南": {
        "draw": false,
        "times": 1
    },
    "華爾滋": {
        "draw": false,
        "times": 3
    },
    "華納": {
        "draw": false,
        "times": 2
    },
    "華語": {
        "draw": false,
        "times": 2
    },
    "藥師": {
        "draw": false,
        "times": 4
    },
    "號": {
        "draw": false,
        "times": 1
    },
    "要充": {
        "draw": false,
        "times": 1
    },
    "要衝": {
        "draw": false,
        "times": 2
    },
    "解除": {
        "draw": false,
        "times": 1
    },
    "評價": {
        "draw": false,
        "times": 1
    },
    "誘因": {
        "draw": false,
        "times": 1
    },
    "說": {
        "draw": false,
        "times": 10
    },
    "請教": {
        "draw": false,
        "times": 1
    },
    "諮詢": {
        "draw": false,
        "times": 3
    },
    "讚": {
        "draw": false,
        "times": 1
    },
    "豐富": {
        "draw": false,
        "times": 2
    },
    "貼": {
        "draw": false,
        "times": 2
    },
    "資訊": {
        "draw": false,
        "times": 3
    },
    "走": {
        "draw": false,
        "times": 2
    },
    "走開": {
        "draw": false,
        "times": 1
    },
    "跟藥": {
        "draw": false,
        "times": 1
    },
    "車上": {
        "draw": false,
        "times": 2
    },
    "辦": {
        "draw": false,
        "times": 2
    },
    "辦法": {
        "draw": false,
        "times": 2
    },
    "退": {
        "draw": false,
        "times": 1
    },
    "退費": {
        "draw": false,
        "times": 4
    },
    "這就": {
        "draw": false,
        "times": 1
    },
    "這是": {
        "draw": false,
        "times": 5
    },
    "這項": {
        "draw": false,
        "times": 1
    },
    "過分": {
        "draw": false,
        "times": 1
    },
    "還好": {
        "draw": false,
        "times": 4
    },
    "邊啊": {
        "draw": false,
        "times": 1
    },
    "邊的": {
        "draw": false,
        "times": 1
    },
    "都給": {
        "draw": false,
        "times": 1
    },
    "配方": {
        "draw": false,
        "times": 1
    },
    "醫不": {
        "draw": false,
        "times": 1
    },
    "醫生": {
        "draw": false,
        "times": 4
    },
    "重考": {
        "draw": false,
        "times": 1
    },
    "開箱": {
        "draw": false,
        "times": 2
    },
    "阿姨": {
        "draw": false,
        "times": 1
    },
    "阿紅": {
        "draw": false,
        "times": 1
    },
    "除夕": {
        "draw": false,
        "times": 5
    },
    "離開": {
        "draw": false,
        "times": 3
    },
    "難搞": {
        "draw": false,
        "times": 2
    },
    "雨": {
        "draw": false,
        "times": 1
    },
    "預計": {
        "draw": false,
        "times": 3
    },
    "飛": {
        "draw": false,
        "times": 3
    },
    "飛機": {
        "draw": false,
        "times": 1
    },
    "餵": {
        "draw": false,
        "times": 2
    },
    "香": {
        "draw": false,
        "times": 1
    },
    "香港": {
        "draw": false,
        "times": 4
    },
    "馬來西亞": {
        "draw": false,
        "times": 2
    },
    "鱷魚": {
        "draw": false,
        "times": 1
    }
}